collective.disqus-2.1-py2.7-nspkg.pth
collective/disqus/__init__.py
collective/disqus/comments.pt
collective/disqus/comments.py
collective/disqus/comments_count.pt
collective/disqus/config.py
collective/disqus/configure.zcml
collective/disqus/controlpanel.py
collective/disqus/disqus_icon.png
collective/disqus/i18n.py
collective/disqus/interfaces.py
collective/disqus/testing.py
collective/disqus/utils.py
collective/disqus/Extensions/Install.py
collective/disqus/Extensions/__init__.py
collective/disqus/browser/__init__.py
collective/disqus/browser/configure.zcml
collective/disqus/browser/disqus_summary_view.pt
collective/disqus/browser/disqus_summary_view.py
collective/disqus/locales/collective.disqus.pot
collective/disqus/locales/manual.pot
collective/disqus/locales/de/LC_MESSAGES/collective.disqus.po
collective/disqus/locales/es/LC_MESSAGES/collective.disqus.po
collective/disqus/locales/fr/LC_MESSAGES/collective.disqus.po
collective/disqus/locales/it/LC_MESSAGES/collective.disqus.po
collective/disqus/locales/pt_BR/LC_MESSAGES/collective.disqus.po
collective/disqus/locales/sl/LC_MESSAGES/collective.disqus.po
collective/disqus/locales/zh_TW/LC_MESSAGES/collective.disqus.po
collective/disqus/portlets/__init__.py
collective/disqus/portlets/configure.zcml
collective/disqus/portlets/hot_threads.pt
collective/disqus/portlets/hot_threads.py
collective/disqus/portlets/popular_threads.pt
collective/disqus/portlets/popular_threads.py
collective/disqus/profiles/default/browserlayer.xml
collective/disqus/profiles/default/controlpanel.xml
collective/disqus/profiles/default/metadata.xml
collective/disqus/profiles/default/portlets.xml
collective/disqus/profiles/default/registry.xml
collective/disqus/profiles/default/types/Collection.xml
collective/disqus/profiles/default/types/Folder.xml
collective/disqus/profiles/test_fixture/metadata.xml
collective/disqus/profiles/test_fixture/registry.xml
collective.disqus-2.1.dist-info/DESCRIPTION.rst
collective.disqus-2.1.dist-info/METADATA
collective.disqus-2.1.dist-info/RECORD
collective.disqus-2.1.dist-info/WHEEL
collective.disqus-2.1.dist-info/entry_points.txt
collective.disqus-2.1.dist-info/metadata.json
collective.disqus-2.1.dist-info/namespace_packages.txt
collective.disqus-2.1.dist-info/top_level.txt
