Metadata-Version: 2.0
Name: collective.disqus
Version: 2.1
Summary: Integration of Disqus comments platform API into Plone.
Home-page: http://github.com/collective/collective.disqus
Author: JeanMichel FRANCOIS aka toutpt
Author-email: toutpt@gmail.com
License: GPLv2
Keywords: plone disqus comments api portlets
Platform: UNKNOWN
Classifier: Development Status :: 5 - Production/Stable
Classifier: Environment :: Web Environment
Classifier: Framework :: Plone
Classifier: Framework :: Plone :: 4.2
Classifier: Framework :: Plone :: 4.3
Classifier: Framework :: Plone :: 5.0
Classifier: Intended Audience :: End Users/Desktop
Classifier: Intended Audience :: System Administrators
Classifier: License :: OSI Approved :: GNU General Public License v2 (GPLv2)
Classifier: Operating System :: OS Independent
Classifier: Programming Language :: JavaScript
Classifier: Programming Language :: Python
Classifier: Programming Language :: Python :: 2.6
Classifier: Programming Language :: Python :: 2.7
Classifier: Topic :: Office/Business :: News/Diary
Classifier: Topic :: Software Development :: Libraries :: Python Modules
Requires-Dist: Products.CMFCore
Requires-Dist: Products.CMFPlone (>=4.2)
Requires-Dist: Products.GenericSetup
Requires-Dist: collective.prettydate
Requires-Dist: disqus-python
Requires-Dist: plone.api
Requires-Dist: plone.app.discussion
Requires-Dist: plone.app.layout
Requires-Dist: plone.app.registry
Requires-Dist: plone.memoize
Requires-Dist: plone.portlets
Requires-Dist: plone.registry
Requires-Dist: setuptools
Requires-Dist: zope.component
Requires-Dist: zope.i18nmessageid
Requires-Dist: zope.interface
Requires-Dist: zope.schema
Provides-Extra: test
Requires-Dist: AccessControl; extra == 'test'
Requires-Dist: plone.app.testing; extra == 'test'
Requires-Dist: plone.browserlayer; extra == 'test'
Requires-Dist: unittest2; extra == 'test'
